{
	"id": "f763f78f-31af-477d-91b9-2d50e7e2bf63",
	"name": "PlatformAPIs-Environment (Template)",
	"values": [
		{
			"key": "anypoint-username",
			"value": "add your values here",
			"enabled": true
		},
		{
			"key": "anypoint-password",
			"value": "add your values here",
			"enabled": true
		},
		{
			"key": "host",
			"value": "anypoint.mulesoft.com",
			"enabled": true
		},
		{
			"key": "api-auth-header",
			"value": "Bearer {{token}}",
			"enabled": true
		},
		{
			"key": "environment-id",
			"value": "follow the tutorial",
			"enabled": true
		},
		{
			"key": "org-id",
			"value": "follow the tutorial",
			"enabled": true
		},
		{
			"key": "business-group-org-id",
			"value": "follow the tutorial",
			"enabled": true
		},
		{
			"key": "domain",
			"value": "",
			"enabled": true
		},
		{
			"key": "search-value",
			"value": "",
			"enabled": true
		},
		{
			"key": "field-display-name",
			"value": "Add your field value",
			"enabled": true
		},
		{
			"key": "field-key",
			"value": "Add your field value",
			"enabled": true
		},
		{
			"key": "asset-name",
			"value": "follow the tutorial",
			"enabled": true
		},
		{
			"key": "asset-version",
			"value": "follow the tutorial",
			"enabled": true
		}
	],
	"_postman_variable_scope": "environment",
	"_postman_exported_at": "2020-07-30T09:12:11.413Z",
	"_postman_exported_using": "Postman/7.28.0"
}